redturtle.prenotazioni-2.8.8-py3.10-nspkg.pth
redturtle/prenotazioni/__init__.py
redturtle/prenotazioni/config.py
redturtle/prenotazioni/configure.zcml
redturtle/prenotazioni/interfaces.py
redturtle/prenotazioni/permissions.zcml
redturtle/prenotazioni/prenotazione_event.py
redturtle/prenotazioni/setuphandlers.py
redturtle/prenotazioni/testing.py
redturtle/prenotazioni/upgrades.py
redturtle/prenotazioni/upgrades.zcml
redturtle/prenotazioni/actions/__init__.py
redturtle/prenotazioni/actions/configure.zcml
redturtle/prenotazioni/actions/mail.py
redturtle/prenotazioni/adapters/__init__.py
redturtle/prenotazioni/adapters/booker.py
redturtle/prenotazioni/adapters/booking_code.py
redturtle/prenotazioni/adapters/configure.zcml
redturtle/prenotazioni/adapters/conflict.py
redturtle/prenotazioni/adapters/ical.py
redturtle/prenotazioni/adapters/prenotazione_menu.py
redturtle/prenotazioni/adapters/slot.py
redturtle/prenotazioni/adapters/stringinterp.py
redturtle/prenotazioni/behaviors/configure.zcml
redturtle/prenotazioni/behaviors/booking_folder/__init__.py
redturtle/prenotazioni/behaviors/booking_folder/configure.zcml
redturtle/prenotazioni/behaviors/booking_folder/contacts.py
redturtle/prenotazioni/behaviors/booking_folder/notifications/__init__.py
redturtle/prenotazioni/behaviors/booking_folder/notifications/configure.zcml
redturtle/prenotazioni/behaviors/booking_folder/notifications/appio/__init__.py
redturtle/prenotazioni/behaviors/booking_folder/notifications/appio/adapters.py
redturtle/prenotazioni/behaviors/booking_folder/notifications/appio/configure.zcml
redturtle/prenotazioni/behaviors/booking_folder/notifications/appio/events.py
redturtle/prenotazioni/behaviors/booking_folder/notifications/appio/notfication_appio_message.py
redturtle/prenotazioni/behaviors/booking_folder/notifications/appio/voc_service_keys.py
redturtle/prenotazioni/behaviors/booking_folder/notifications/email/__init__.py
redturtle.prenotazioni-2.8.8.dist-info/LICENSE.GPL
redturtle.prenotazioni-2.8.8.dist-info/LICENSE.rst
redturtle.prenotazioni-2.8.8.dist-info/METADATA
redturtle.prenotazioni-2.8.8.dist-info/WHEEL
redturtle.prenotazioni-2.8.8.dist-info/entry_points.txt
redturtle.prenotazioni-2.8.8.dist-info/namespace_packages.txt
redturtle.prenotazioni-2.8.8.dist-info/top_level.txt
redturtle.prenotazioni-2.8.8.dist-info/RECORD
