Metadata-Version: 2.1
Name: redturtle.prenotazioni
Version: 2.8.8
Summary: An add-on for Plone
Home-page: https://github.com/redturtle/redturtle.prenotazioni
Author: RedTurtle Technology
Author-email: sviluppoplone@redturtle.it
License: GPL version 2
Project-URL: PyPI, https://pypi.org/project/redturtle.prenotazioni
Project-URL: Source, https://github.com/redturtle/redturtle.prenotazioni
Project-URL: Tracker, https://github.com/redturtle/redturtle.prenotazioni/issues
Keywords: Python Plone
Classifier: Development Status :: 5 - Production/Stable
Classifier: Environment :: Web Environment
Classifier: Framework :: Plone
Classifier: Framework :: Plone :: Addon
Classifier: Framework :: Plone :: 5.2
Classifier: Framework :: Plone :: 6.0
Classifier: Programming Language :: Python
Classifier: Programming Language :: Python :: 3.8
Classifier: Programming Language :: Python :: 3.9
Classifier: Programming Language :: Python :: 3.10
Classifier: Programming Language :: Python :: 3.11
Classifier: Operating System :: OS Independent
Classifier: License :: OSI Approved :: GNU General Public License v2 (GPLv2)
Requires-Python: >=3.8
License-File: LICENSE.GPL
License-File: LICENSE.rst
Requires-Dist: setuptools
Requires-Dist: z3c.jbot
Requires-Dist: plone.api >=1.8.4
Requires-Dist: plone.restapi >=8.38.0
Requires-Dist: collective.contentrules.mailfromfield >=1.2.0
Requires-Dist: pyinter
Requires-Dist: collective.honeypot
Requires-Dist: collective.z3cform.datagridfield >=2.0
Requires-Dist: pyexcel-xlsx
Requires-Dist: click
Requires-Dist: qrcode
Requires-Dist: plone.app.caching >=3.0.0a1
Requires-Dist: bravado
Provides-Extra: app_io
Requires-Dist: bravado ; extra == 'app_io'
Requires-Dist: pytz ; extra == 'app_io'
Provides-Extra: plone5
Requires-Dist: collective.dexteritytextindexer ; extra == 'plone5'
Provides-Extra: test
Requires-Dist: plone.app.testing ; extra == 'test'
Requires-Dist: plone.testing >=5.0.0 ; extra == 'test'
Requires-Dist: plone.app.contenttypes[test] ; extra == 'test'
Requires-Dist: collective.MockMailHost ; extra == 'test'
Requires-Dist: freezegun ; extra == 'test'
